setup.py
ovi_distributionpackage/Binomialdistribution.py
ovi_distributionpackage/Gaussiandistribution.py
ovi_distributionpackage/Generaldistribution.py
ovi_distributionpackage/__init__.py
ovi_distributionpackage.egg-info/PKG-INFO
ovi_distributionpackage.egg-info/SOURCES.txt
ovi_distributionpackage.egg-info/dependency_links.txt
ovi_distributionpackage.egg-info/not-zip-safe
ovi_distributionpackage.egg-info/top_level.txt