Metadata-Version: 1.0
Name: ovi-distributionpackage
Version: 0.2
Summary: Gaussian & Binomial distributions
Home-page: UNKNOWN
Author: Muhammad Ovais
Author-email: movais996@gmail.com
License: UNKNOWN
Platform: UNKNOWN
